browserstate/__init__.py
browserstate/browser_state.py
browserstate/storage/__init__.py
browserstate/storage/gcs_storage.py
browserstate/storage/local_storage.py
browserstate/storage/redis_storage.py
browserstate/storage/s3_storage.py
browserstate/storage/storage_provider.py
browserstate/utils/__init__.py
browserstate/utils/dynamic_import.py
browserstate-0.0.4.dist-info/METADATA
browserstate-0.0.4.dist-info/WHEEL
browserstate-0.0.4.dist-info/licenses/LICENSE
browserstate-0.0.4.dist-info/RECORD
