Metadata-Version: 2.4
Name: browserstate
Version: 0.0.4
Summary: Manage browser profiles across cloud storage providers
Project-URL: Homepage, https://browserstate.io
Project-URL: Documentation, https://browserstate.io
Project-URL: Repository, https://github.com/browserstate-org/browserstate
Project-URL: Issues, https://github.com/browserstate-org/browserstate/issues
Project-URL: GitHub Packages, https://github.com/browserstate-org/browserstate/packages
Author-email: BrowserState Team <info@browserstate.dev>
License-Expression: MIT
License-File: LICENSE
Classifier: License :: OSI Approved :: MIT License
Classifier: Operating System :: OS Independent
Classifier: Programming Language :: Python :: 3
Requires-Python: >=3.8
Provides-Extra: all
Requires-Dist: boto3>=1.26.0; extra == 'all'
Requires-Dist: google-cloud-storage>=2.7.0; extra == 'all'
Requires-Dist: redis>=4.5.0; extra == 'all'
Provides-Extra: dev
Requires-Dist: flake8>=6.0.0; extra == 'dev'
Requires-Dist: moto>=5.0.0; extra == 'dev'
Requires-Dist: pytest-asyncio>=0.23.0; extra == 'dev'
Requires-Dist: pytest-cov>=4.0.0; extra == 'dev'
Requires-Dist: pytest>=7.0.0; extra == 'dev'
Requires-Dist: ruff>=0.3.0; extra == 'dev'
Provides-Extra: gcs
Requires-Dist: google-cloud-storage>=2.7.0; extra == 'gcs'
Provides-Extra: redis
Requires-Dist: redis>=4.5.0; extra == 'redis'
Provides-Extra: s3
Requires-Dist: boto3>=1.26.0; extra == 's3'
